xgp.cpython-35m-x86_64-linux-gnu.h
xgp.cpython-35m-x86_64-linux-gnu.so
examples/boston_regression.py
examples/__init__.py
examples/breast_cancer_classification.py
xgp/classification.py
xgp/parse.py
xgp/__init__.py
xgp/binding.py
xgp/regression.py
xgp/model.py
xgp/tests/test_binding.py
xgp/tests/__init__.py
xgp/tests/test_classifier.py
xgp/tests/test_regressor.py
xgp-0.1.1.dist-info/WHEEL
xgp-0.1.1.dist-info/top_level.txt
xgp-0.1.1.dist-info/METADATA
xgp-0.1.1.dist-info/RECORD
