Metadata-Version: 2.1
Name: xgp
Version: 0.1.1
Summary: XGP Python package with a scikit-learn interface
Home-page: https://maxhalford.github.io/xgp
Author: Max Halford
Author-email: maxhalford25@gmail.com
License: UNKNOWN
Platform: UNKNOWN
Requires-Dist: pytest (>=3.5.1)
Requires-Dist: pytest-cov (>=2.6.0)
Requires-Dist: scikit-learn (>=0.17)
